{"66929e298a431d5eac1773bd":{"skills":["sql","oracle","play"],"experience":null},"66929e298a431d5eac1773be":{"skills":["medium"],"experience":3},"66929e298a431d5eac1773bf":{"skills":["python","java","ruby","golang","powershell","perl","linux"],"experience":4},"66929e298a431d5eac1773c0":{"skills":["play","echo"],"experience":5},"66929e298a431d5eac1773c1":{"skills":["selenium","medium","appium"],"experience":4},"66929e298a431d5eac1773c2":{"skills":[],"experience":null},"66929e298a431d5eac1773c3":{"skills":[],"experience":null},"66929e298a431d5eac1773c4":{"skills":[],"experience":null},"66929e298a431d5eac1773c5":{"skills":[],"experience":null},"66929e298a431d5eac1773c6":{"skills":[],"experience":null}}